psy_strat/__init__.py
psy_strat/plotters.py
psy_strat/plugin.py
psy_strat/strat_widget.py
psy_strat/stratplot.py
psy_strat-0.1.2.dist-info/licenses/LICENSE
psy_strat-0.1.2.dist-info/METADATA
psy_strat-0.1.2.dist-info/WHEEL
psy_strat-0.1.2.dist-info/entry_points.txt
psy_strat-0.1.2.dist-info/top_level.txt
psy_strat-0.1.2.dist-info/RECORD
