Metadata-Version: 2.4
Name: psy-strat
Version: 0.1.2
Summary: A psyplot plugin for stratigraphic plots
Home-page: https://github.com/Chilipp/psy-strat
Author: Philipp Sommer
Author-email: philipp.sommer@unil.ch
License: GPLv2
Keywords: visualization psyplot pollen
Classifier: Development Status :: 7 - Inactive
Classifier: Intended Audience :: Developers
Classifier: Topic :: Scientific/Engineering :: Visualization
Classifier: Topic :: Scientific/Engineering
Classifier: License :: OSI Approved :: GNU General Public License v2 (GPLv2)
Classifier: Programming Language :: Python :: 3.6
Classifier: Programming Language :: Python :: 3.7
Classifier: Operating System :: OS Independent
License-File: LICENSE
Requires-Dist: psyplot>=1.2.0
Requires-Dist: psy-simple>=1.2.0
Requires-Dist: xarray!=0.13.0
Dynamic: author
Dynamic: author-email
Dynamic: classifier
Dynamic: description
Dynamic: home-page
Dynamic: keywords
Dynamic: license
Dynamic: license-file
Dynamic: requires-dist
Dynamic: summary
